mexican_sign_language_toolkit/__init__.py
mexican_sign_language_toolkit/cli.py
mexican_sign_language_toolkit/lexer.py
mexican_sign_language_toolkit/neighbors.py
mexican_sign_language_toolkit/numpy_cache.py
mexican_sign_language_toolkit/pipeline.py
mexican_sign_language_toolkit/pose_landmarker.py
mexican_sign_language_toolkit/server.py
mexican_sign_language_toolkit-1.0.9.dist-info/LICENSE.txt
mexican_sign_language_toolkit-1.0.9.dist-info/METADATA
mexican_sign_language_toolkit-1.0.9.dist-info/WHEEL
mexican_sign_language_toolkit-1.0.9.dist-info/entry_points.txt
mexican_sign_language_toolkit-1.0.9.dist-info/top_level.txt
mexican_sign_language_toolkit-1.0.9.dist-info/RECORD
