Metadata-Version: 2.1
Name: mexican-sign-language-toolkit
Version: 1.0.9
Summary: Manage visual language with msl
Home-page: https://github.com/sanchezcarlosjr/mexican_sign_language_toolkit/
Author: sanchezcarlosjr
Author-email: 24639141+sanchezcarlosjr@users.noreply.github.com
License: MIT
Project-URL: Documentation, https://github.com/sanchezcarlosjr/mexican_sign_language_toolkit/
Platform: any
Classifier: Development Status :: 4 - Beta
Classifier: Programming Language :: Python
License-File: LICENSE.txt
Requires-Dist: opencv-python
Requires-Dist: mediapipe
Requires-Dist: regex
Requires-Dist: scipy
Requires-Dist: gradio
Requires-Dist: uuid7
Requires-Dist: scikit-learn
Requires-Dist: xxhash
Requires-Dist: importlib-metadata ; python_version < "3.8"
Provides-Extra: testing
Requires-Dist: setuptools ; extra == 'testing'
Requires-Dist: pytest ; extra == 'testing'
Requires-Dist: pytest-cov ; extra == 'testing'
